{
  "latinName": "Valeriana capitata - Pall.",
  "commonName": "Valerian, Captiate valerian",
  "family": "Valerianaceae",
  "usdaHardiness": "Coming soon",
  "knownHazards": "Some caution is advised with the use of this plant. At least one member of the genus is considered to be poisonous raw[161] and V. officinalis is a powerful nervine and sedative that can become habit-forming.",
  "habitats": "Boggy meadows and moist slopes in Alaska[172].",
  "range": "North-western N. America.",
  "edibilityRating": "(1 of 5)",
  "otherUsesRating": "(1 of 5)",
  "weedPotential": "No",
  "medicinalRating": "(1 of 5)",
  "physicalCharacteristics": "Valeriana capitata is a PERENNIAL growing to 0.6 m (2ft). The species is hermaphrodite (has both male and female organs) and is pollinated by Insects.  Suitable for: light (sandy), medium (loamy) and heavy (clay) soils. Suitable pH: mildly acid, neutral and basic (mildly alkaline) soils. It cannot grow in the shade. It prefers  moist or  wet soil.",
  "synonyms": "",
  "plantHabitats": "Bog Garden; Cultivated Beds;",
  "edibleUses": "Edible Parts: Root  SeedEdible Uses: Seed - parched[172]. Root - steamed for 24 hours[172].",
  "medicinalUses": "Plants For A Future can not take any responsibility for any adverse effects from the use of plants. Always seek advice from a professional before using a plant medicinally.Antispasmodic  Carminative  Diuretic  Hypnotic  Nervine  Sedative  StimulantThe whole plant, but especially the root, is antispasmodic, carminative, diuretic, hypnotic, powerfully nervine, sedative and stimulant[172]. Use with caution[21].",
  "otherUses": "IncenseThe dried root has been used as an incense[257].",
  "specialUses": "",
  "cultivationDetails": "Succeeds in ordinary garden soil[1]. Judging by the plants native habitat, it should also succeed in wet soils[172].",
  "propagation": "Seed - sow spring in a cold frame and only just cover the seed because it requires light for germination[200]. Prick out the seedlings into individual pots when they are large enough to handle and plant out into their permanent positions in the summer if sufficient growth has been made. If the plants are too small to plant out, grow them on in the greenhouse or frame for their first winter and plant them out early in the following summer. Division in spring. Larger divisions can be planted out direct into their permanent positions. We have found that it is best to pot up smaller divisions and grow them on in light shade in a greenhouse or cold frame until they are growing away well. Plant them out in the summer or the following spring.",
  "otherNames": "",
  "nativeRange": "TEMPERATE ASIA: Mongolia, Russian Federation (Kamcatskij kraj, Cukotskij avtonomnyj okrug, Sakhalin) NORTHERN AMERICA: Canada (Yukon, British Columbia), United States (Alaska) EUROPE: Russian Federation (Arkhangelsk)",
  "weedPotentialText": "",
  "conservationStatus": "IUCN Red List of Threatened Plants Status :",
  "relatedPlants": [
    {
      "latinName": "Centranthus macrosiphon",
      "commonName": "",
      "habit": "Annual",
      "height": "0.6",
      "hardiness": "-",
      "growth": "",
      "soil": "LMH",
      "shade": "N",
      "moisture": "DM",
      "edible": "2",
      "medicinal": "0",
      "otherUses": ""
    },
    {
      "latinName": "Centranthus ruber",
      "commonName": "Red Valerian, Fox's Brush, Jupiter's Beard",
      "habit": "Perennial",
      "height": "0.9",
      "hardiness": "5-8",
      "growth": "M",
      "soil": "LMH",
      "shade": "N",
      "moisture": "DM",
      "edible": "2",
      "medicinal": "1",
      "otherUses": "1"
    },
    {
      "latinName": "Fedia cornucopiae",
      "commonName": "",
      "habit": "Annual",
      "height": "0.2",
      "hardiness": "-",
      "growth": "",
      "soil": "LMH",
      "shade": "N",
      "moisture": "DM",
      "edible": "2",
      "medicinal": "0",
      "otherUses": ""
    },
    {
      "latinName": "Nardostachys grandiflora",
      "commonName": "Spikenard",
      "habit": "Perennial",
      "height": "0.3",
      "hardiness": "-",
      "growth": "",
      "soil": "LMH",
      "shade": "SN",
      "moisture": "M",
      "edible": "1",
      "medicinal": "3",
      "otherUses": "3"
    },
    {
      "latinName": "Patrinia scabiosifolia",
      "commonName": "Eastern Valerian, Scabious Patrinia",
      "habit": "Perennial",
      "height": "0.6",
      "hardiness": "5-8",
      "growth": "F",
      "soil": "LM",
      "shade": "N",
      "moisture": "M",
      "edible": "1",
      "medicinal": "3",
      "otherUses": ""
    },
    {
      "latinName": "Patrinia triloba",
      "commonName": "",
      "habit": "Perennial",
      "height": "0.5",
      "hardiness": "-",
      "growth": "",
      "soil": "LMH",
      "shade": "SN",
      "moisture": "M",
      "edible": "1",
      "medicinal": "0",
      "otherUses": "2"
    },
    {
      "latinName": "Patrinia villosa",
      "commonName": "",
      "habit": "Perennial",
      "height": "1.0",
      "hardiness": "-",
      "growth": "",
      "soil": "LMH",
      "shade": "SN",
      "moisture": "M",
      "edible": "1",
      "medicinal": "1",
      "otherUses": ""
    },
    {
      "latinName": "Valeriana amurensis",
      "commonName": "",
      "habit": "Perennial",
      "height": "0.0",
      "hardiness": "-",
      "growth": "",
      "soil": "LMH",
      "shade": "N",
      "moisture": "M",
      "edible": "1",
      "medicinal": "0",
      "otherUses": ""
    },
    {
      "latinName": "Valeriana celtica",
      "commonName": "",
      "habit": "Perennial",
      "height": "0.3",
      "hardiness": "-",
      "growth": "",
      "soil": "LMH",
      "shade": "N",
      "moisture": "M",
      "edible": "1",
      "medicinal": "1",
      "otherUses": "2"
    },
    {
      "latinName": "Valeriana ciliata",
      "commonName": "Tobacco Root",
      "habit": "Perennial",
      "height": "0.8",
      "hardiness": "-",
      "growth": "",
      "soil": "LMH",
      "shade": "N",
      "moisture": "M",
      "edible": "1",
      "medicinal": "0",
      "otherUses": ""
    },
    {
      "latinName": "Valeriana dioica",
      "commonName": "Marsh Valerian, Woods valerian",
      "habit": "Perennial",
      "height": "0.3",
      "hardiness": "0-0",
      "growth": "",
      "soil": "LMH",
      "shade": "N",
      "moisture": "MWe",
      "edible": "1",
      "medicinal": "1",
      "otherUses": ""
    },
    {
      "latinName": "Valeriana fauriei",
      "commonName": "",
      "habit": "Perennial",
      "height": "1.0",
      "hardiness": "-",
      "growth": "",
      "soil": "LMH",
      "shade": "N",
      "moisture": "M",
      "edible": "0",
      "medicinal": "1",
      "otherUses": ""
    },
    {
      "latinName": "Valeriana hardwickii",
      "commonName": "",
      "habit": "Perennial",
      "height": "1.5",
      "hardiness": "-",
      "growth": "",
      "soil": "LMH",
      "shade": "N",
      "moisture": "M",
      "edible": "0",
      "medicinal": "3",
      "otherUses": "2"
    },
    {
      "latinName": "Valeriana jatamansi",
      "commonName": "Indian Valerian",
      "habit": "Perennial",
      "height": "0.5",
      "hardiness": "-",
      "growth": "",
      "soil": "LMH",
      "shade": "N",
      "moisture": "M",
      "edible": "0",
      "medicinal": "3",
      "otherUses": "1"
    },
    {
      "latinName": "Valeriana obovata",
      "commonName": "Tobacco Root",
      "habit": "Perennial",
      "height": "1.2",
      "hardiness": "-",
      "growth": "",
      "soil": "LMH",
      "shade": "N",
      "moisture": "M",
      "edible": "2",
      "medicinal": "1",
      "otherUses": ""
    },
    {
      "latinName": "Valeriana occidentalis",
      "commonName": "western valerian",
      "habit": "Perennial",
      "height": "1.0",
      "hardiness": "-",
      "growth": "",
      "soil": "LMH",
      "shade": "N",
      "moisture": "M",
      "edible": "1",
      "medicinal": "1",
      "otherUses": ""
    },
    {
      "latinName": "Valeriana officinalis",
      "commonName": "Valerian, Garden valerian",
      "habit": "Perennial",
      "height": "1.5",
      "hardiness": "4-8",
      "growth": "M",
      "soil": "LMH",
      "shade": "N",
      "moisture": "M",
      "edible": "2",
      "medicinal": "3",
      "otherUses": "3"
    },
    {
      "latinName": "Valeriana phu",
      "commonName": "",
      "habit": "Perennial",
      "height": "0.4",
      "hardiness": "-",
      "growth": "",
      "soil": "LMH",
      "shade": "SN",
      "moisture": "DM",
      "edible": "2",
      "medicinal": "1",
      "otherUses": "3"
    },
    {
      "latinName": "Valeriana sambucifolia",
      "commonName": "",
      "habit": "Perennial",
      "height": "1.5",
      "hardiness": "4-8",
      "growth": "",
      "soil": "LMH",
      "shade": "SN",
      "moisture": "M",
      "edible": "2",
      "medicinal": "3",
      "otherUses": "2"
    },
    {
      "latinName": "Valeriana sitchensis",
      "commonName": "American Valerian, Sitka valerian",
      "habit": "Perennial",
      "height": "1.2",
      "hardiness": "0-0",
      "growth": "",
      "soil": "LMH",
      "shade": "N",
      "moisture": "M",
      "edible": "1",
      "medicinal": "3",
      "otherUses": "1"
    },
    {
      "latinName": "Valeriana toluccana",
      "commonName": "",
      "habit": "Perennial",
      "height": "0.0",
      "hardiness": "-",
      "growth": "",
      "soil": "LMH",
      "shade": "N",
      "moisture": "M",
      "edible": "2",
      "medicinal": "2",
      "otherUses": "3"
    },
    {
      "latinName": "Valeriana uliginosa",
      "commonName": "Mountain Valerian",
      "habit": "Perennial",
      "height": "1.0",
      "hardiness": "-",
      "growth": "",
      "soil": "LMH",
      "shade": "N",
      "moisture": "MWe",
      "edible": "0",
      "medicinal": "2",
      "otherUses": ""
    },
    {
      "latinName": "Valerianella carinata",
      "commonName": "Keeled-Fruited Cornsalad, European cornsalad",
      "habit": "Annual",
      "height": "0.3",
      "hardiness": "0-0",
      "growth": "",
      "soil": "LMH",
      "shade": "N",
      "moisture": "DM",
      "edible": "2",
      "medicinal": "0",
      "otherUses": ""
    },
    {
      "latinName": "Valerianella chenopodifolia",
      "commonName": "",
      "habit": "Annual",
      "height": "0.6",
      "hardiness": "-",
      "growth": "",
      "soil": "LMH",
      "shade": "N",
      "moisture": "M",
      "edible": "2",
      "medicinal": "0",
      "otherUses": ""
    },
    {
      "latinName": "Valerianella eriocarpa",
      "commonName": "Italian Corn Salad",
      "habit": "Annual",
      "height": "0.4",
      "hardiness": "-",
      "growth": "",
      "soil": "LMH",
      "shade": "N",
      "moisture": "DM",
      "edible": "3",
      "medicinal": "0",
      "otherUses": ""
    },
    {
      "latinName": "Valerianella locusta",
      "commonName": "Corn Salad, Lewiston cornsalad",
      "habit": "Annual",
      "height": "0.3",
      "hardiness": "4-8",
      "growth": "",
      "soil": "LMH",
      "shade": "N",
      "moisture": "DM",
      "edible": "4",
      "medicinal": "0",
      "otherUses": ""
    },
    {
      "latinName": "Valerianella radiata",
      "commonName": "Beaked Cornsalad",
      "habit": "Annual",
      "height": "0.6",
      "hardiness": "0-0",
      "growth": "",
      "soil": "LMH",
      "shade": "N",
      "moisture": "DM",
      "edible": "2",
      "medicinal": "0",
      "otherUses": "0"
    }
  ],
  "images": [
    {
      "src": "../Admin/PlantImages/ValerianaCapitata.jpg",
      "alt": "Valeriana capitata Valerian, Captiate valerian",
      "title": "Valeriana capitata Valerian, Captiate valerian",
      "width": "100%"
    },
    {
      "src": "../Admin/PlantImages/ValerianaCapitata2.jpg",
      "alt": "Valeriana capitata Valerian, Captiate valerian",
      "title": "Valeriana capitata Valerian, Captiate valerian",
      "width": "240"
    }
  ],
  "careIcons": [
    {
      "src": "../user/images/PFAF_Icon/water2.jpg",
      "alt": "Moist Soil",
      "title": "Moist Soil"
    },
    {
      "src": "../user/images/PFAF_Icon/water3.jpg",
      "alt": "Wet Soil",
      "title": "Wet Soil"
    },
    {
      "src": "../user/images/PFAF_Icon/sun.jpg",
      "alt": "Full sun",
      "title": "Full sun"
    }
  ],
  "metaDescription": "Valeriana capitata is a PERENNIAL growing to 0.6 m (2ft). The species is hermaphrodite (has both male and female organs) and is pollinated by Insects.  Suitable for: light (sandy), medium (loamy) and heavy (clay) soils. Suitable pH: mildly acid, neutral and basic (mildly alkaline) soils. It cannot grow in the shade. It prefers  moist or  wet soil.",
  "pageTitle": "Valeriana capitata Valerian, Captiate valerian PFAF Plant Database"
}